elevator_pitch_faker/__init__.py
elevator_pitch_faker/story.py
elevator_pitch_faker-0.2.0.dist-info/DESCRIPTION.rst
elevator_pitch_faker-0.2.0.dist-info/METADATA
elevator_pitch_faker-0.2.0.dist-info/RECORD
elevator_pitch_faker-0.2.0.dist-info/WHEEL
elevator_pitch_faker-0.2.0.dist-info/metadata.json
elevator_pitch_faker-0.2.0.dist-info/top_level.txt
elevator_pitch_faker-0.2.0.dist-info/zip-safe
