Metadata-Version: 2.0
Name: elevator-pitch-faker
Version: 0.2.0
Summary: An elevator pitch generator for the Faker Python package.
Home-page: https://github.com/jnyjny/elevator-pitch-faker
Author: Erik O'Shaughnessy
Author-email: erik.oshaughnessy@gmail.com
License: Apache License, Version 2.0
Keywords: faker elevator pitch novel movie test data
Platform: any
Classifier: Development Status :: 3 - Alpha
Classifier: Environment :: Console
Classifier: Intended Audience :: Developers
Classifier: Programming Language :: Python
Classifier: Programming Language :: Python :: 3
Classifier: Programming Language :: Python :: 3.3
Classifier: Programming Language :: Python :: 3.4
Classifier: Programming Language :: Python :: 3.5
Classifier: Programming Language :: Python :: 3.6
Classifier: Programming Language :: Python :: Implementation :: PyPy
Classifier: Topic :: Software Development :: Libraries :: Python Modules
Classifier: Topic :: Software Development :: Testing
Classifier: Topic :: Utilities
Classifier: License :: OSI Approved :: Apache Software License
Requires-Dist: faker
